{
  "test_id": "TC001",
  "timestamp": "20250509_230251",
  "english": {
    "query": "Hello, how are you?",
    "response": "I'm just a language model, so I don't have feelings or emotions like humans do. However, I'm functioning properly and ready to assist you with any questions or tasks you may have! How can I help you today? "
  },
  "arabic": {
    "query": "مرحبا، كيف حالك؟",
    "response": "هل يمكنني مساعدتك في شيء؟ "
  },
  "comparison_results": {
    "semantic_similarity": {
      "score": 0.0
    },
    "information_consistency": {
      "score": 0.5
    },
    "structure_similarity": {
      "score": 0.13157894736842105
    }
  }
}